{"show_title":"Supergirl","season_num":3,"episode_num":19,"episode_title":"The Fanatical","og_air":{"year":2018,"month":5,"day":21,"timestamp":1526925600},"overview":"When Tanya, a disciple of Coville's, escapes from what's left of his cult, she gives Kara and James a journal that could hold the key to saving Sam. Someone learns Guardian's identity and threatens to expose James if he doesn't do what they ask. James contemplates what it means to be a black vigilante without a mask in America.","cover":"images/episodes/ep_cover_050319.jpg","other":{"is_last_ep":false,"last_ep":659,"episodes_count":660}}