{"show_title":"Supergirl","season_num":4,"episode_num":5,"episode_title":"Parasite Lost","og_air":{"year":2018,"month":11,"day":11,"timestamp":1541962800},"overview":"Colonel Haley makes a surprising decision regarding Supergirl. Kara writes a series of articles highlighting aliens in National City in the hopes that humans will stop being so fearful of them. Unfortunately, the article puts some of the aliens in harm\u2019s way.","cover":"images/episodes/ep_cover_050405.jpg","other":{"is_last_ep":false,"last_ep":659,"episodes_count":660}}