{"show_title":"The Flash","season_num":6,"episode_num":18,"episode_title":"Pay the Piper","og_air":{"year":2020,"month":5,"day":5,"timestamp":1588701600},"overview":"When Godspeed returns, Barry turns to Hartley Rathaway for help. However, things get tense quickly after Barry realizes one of the changes from Crisis is that The Flash and Pied Piper are now enemies. Meanwhile, Iris tries to escape the Mirrorverse.","cover":"images/episodes/ep_cover_020618.jpg","other":{"is_last_ep":false,"last_ep":659,"episodes_count":660}}